vitmem/__init__.py
vitmem-1.0.0.dist-info/LICENSE
vitmem-1.0.0.dist-info/METADATA
vitmem-1.0.0.dist-info/WHEEL
vitmem-1.0.0.dist-info/top_level.txt
vitmem-1.0.0.dist-info/RECORD
