Metadata-Version: 2.1
Name: vitmem
Version: 1.0.0
Summary: A package for estimating image memorability
Home-page: https://github.com/brainpriority/vitmem
Author: Brain Priority Lab
Author-email: mail@brainpriority.com
Project-URL: Bug Tracker, https://github.com/brainpriority/vitmem/issues
Classifier: Programming Language :: Python :: 3
Classifier: License :: OSI Approved :: MIT License
Classifier: Operating System :: OS Independent
Requires-Python: >=3.6
License-File: LICENSE
